skdda/__init__.py
skdda/base.py
tests/__init__.py
tests/test_base.py
scikit_dda-0.1.1.dist-info/LICENSE
scikit_dda-0.1.1.dist-info/METADATA
scikit_dda-0.1.1.dist-info/WHEEL
scikit_dda-0.1.1.dist-info/top_level.txt
scikit_dda-0.1.1.dist-info/RECORD
